{
    "company_info": {
        "name": "SpiceBox",
        "url": "https://yoursite.com",
        "product_description": "SpiceBox — cloud kitchen food delivery Chennai"
    },
    "company_keywords": {
        "short_keywords": [],
        "long_tail_keywords": []
    },
    "competitor_analysis": {
        "competitors_analyzed": 6,
        "competitor_details": [
            {
                "name": "CloudKitchens: Technology optimized for Delivery + Pickup",
                "url": "https://cloudkitchens.com/",
                "short_keywords_count": 0,
                "long_tail_keywords_count": 0
            },
            {
                "name": "Postmates: Food Delivery, Groceries, Alcohol - Anything from ...",
                "url": "https://postmates.com/",
                "short_keywords_count": 12,
                "long_tail_keywords_count": 1
            },
            {
                "name": "Meal Delivery Software",
                "url": "https://www.mealdeliverysoftware.com/",
                "short_keywords_count": 5,
                "long_tail_keywords_count": 0
            },
            {
                "name": "White Label Grocery eCommerce Software Platform Solution",
                "url": "https://mycloudgrocer.com/",
                "short_keywords_count": 25,
                "long_tail_keywords_count": 25
            },
            {
                "name": "MealTrack Meal Prep Software for your Meal Prep Business ...",
                "url": "https://www.mealtrack.com/",
                "short_keywords_count": 25,
                "long_tail_keywords_count": 25
            },
            {
                "name": "GloriaFood Online Ordering: Free Online Ordering System for ...",
                "url": "https://www.gloriafood.com/",
                "short_keywords_count": 25,
                "long_tail_keywords_count": 25
            }
        ]
    },
    "gap_analysis": {
        "missing_keywords": {
            "short": [
                "social media",
                "order",
                "restaurant widgets",
                "statistics drawn",
                "wed love",
                "cannot find",
                "qr code",
                "seconds clip",
                "needed",
                "puts dedicated"
            ],
            "long_tail": [
                "help supermarkets thrive",
                "best online ordering system",
                "online site went live",
                "store process efficiencies save",
                "online ordering system",
                "highly secure data processes",
                "free restaurant ordering system",
                "clients contact us designedexclusively",
                "food waste reducing costs",
                "mealtrack benefits testimonials mealtrack"
            ]
        },
        "unique_company_keywords": {
            "short": [],
            "long_tail": []
        },
        "organic_opportunities": {
            "short": [
                "social media",
                "order",
                "restaurant widgets",
                "statistics drawn",
                "wed love"
            ],
            "long_tail": [
                "help supermarkets thrive",
                "best online ordering system",
                "online site went live",
                "store process efficiencies save",
                "online ordering system"
            ]
        },
        "recommendations": [
            "Incorporate missing short and long-tail keywords into SpiceBox's website content and meta tags",
            "Develop a social media presence to target relevant keywords and increase brand visibility",
            "Implement a secure online ordering system to attract clients and reduce food waste",
            "Optimize the website for SEO by using keywords in headings, subheadings, and body content",
            "Create a blog to publish articles related to the food delivery industry and target long-tail keywords"
        ],
        "competitive_insights": [
            "Competitors are using social media to their advantage, indicating a need for SpiceBox to develop a strong social media presence",
            "The use of restaurant widgets and QR codes by competitors suggests a focus on user experience and convenience",
            "The presence of statistics and data-driven content on competitors' websites highlights the importance of showcasing SpiceBox's own data and successes"
        ]
    },
    "summary": {
        "missing_short_keywords": 10,
        "missing_long_tail_keywords": 10,
        "unique_company_keywords": 0,
        "organic_opportunities": 10
    }
}